MANIFEST.in
README.rst
setup.cfg
setup.py
docs/CREDITS.rst
docs/HISTORY.rst
docs/LICENSE.GPL
docs/LICENSE.txt
src/sc/__init__.py
src/sc.contentrules.groupbydate.egg-info/PKG-INFO
src/sc.contentrules.groupbydate.egg-info/SOURCES.txt
src/sc.contentrules.groupbydate.egg-info/dependency_links.txt
src/sc.contentrules.groupbydate.egg-info/entry_points.txt
src/sc.contentrules.groupbydate.egg-info/namespace_packages.txt
src/sc.contentrules.groupbydate.egg-info/not-zip-safe
src/sc.contentrules.groupbydate.egg-info/requires.txt
src/sc.contentrules.groupbydate.egg-info/top_level.txt
src/sc/contentrules/__init__.py
src/sc/contentrules/groupbydate/__init__.py
src/sc/contentrules/groupbydate/config.py
src/sc/contentrules/groupbydate/configure.zcml
src/sc/contentrules/groupbydate/events.py
src/sc/contentrules/groupbydate/interfaces.py
src/sc/contentrules/groupbydate/testing.py
src/sc/contentrules/groupbydate/vocabulary.py
src/sc/contentrules/groupbydate/actions/__init__.py
src/sc/contentrules/groupbydate/actions/groupbydate.py
src/sc/contentrules/groupbydate/locales/manual.pot
src/sc/contentrules/groupbydate/locales/plone.pot
src/sc/contentrules/groupbydate/locales/sc.contentrules.groupbydate.pot
src/sc/contentrules/groupbydate/locales/es/LC_MESSAGES/plone.mo
src/sc/contentrules/groupbydate/locales/es/LC_MESSAGES/plone.po
src/sc/contentrules/groupbydate/locales/es/LC_MESSAGES/sc.contentrules.groupbydate.mo
src/sc/contentrules/groupbydate/locales/es/LC_MESSAGES/sc.contentrules.groupbydate.po
src/sc/contentrules/groupbydate/locales/it/LC_MESSAGES/plone.mo
src/sc/contentrules/groupbydate/locales/it/LC_MESSAGES/plone.po
src/sc/contentrules/groupbydate/locales/it/LC_MESSAGES/sc.contentrules.groupbydate.mo
src/sc/contentrules/groupbydate/locales/it/LC_MESSAGES/sc.contentrules.groupbydate.po
src/sc/contentrules/groupbydate/locales/pt_BR/LC_MESSAGES/plone.mo
src/sc/contentrules/groupbydate/locales/pt_BR/LC_MESSAGES/plone.po
src/sc/contentrules/groupbydate/locales/pt_BR/LC_MESSAGES/sc.contentrules.groupbydate.mo
src/sc/contentrules/groupbydate/locales/pt_BR/LC_MESSAGES/sc.contentrules.groupbydate.po
src/sc/contentrules/groupbydate/tests/__init__.py
src/sc/contentrules/groupbydate/tests/controlpanel.txt
src/sc/contentrules/groupbydate/tests/test_action_groupbydate.py
src/sc/contentrules/groupbydate/tests/test_functional.py