Metadata-Version: 1.1
Name: sc.contentrules.groupbydate
Version: 2.0.1
Summary: A Plone content rules action that creates a chronological archive.
Home-page: http://www.simplesconsultoria.com.br/
Author: Simples Consultoria
Author-email: products@simplesconsultoria.com.br
License: GPLv2
Keywords: plone contentrules actions date grouping
Platform: UNKNOWN
Classifier: Development Status :: 5 - Production/Stable
Classifier: Environment :: Web Environment
Classifier: Framework :: Plone
Classifier: Framework :: Plone :: 4.2
Classifier: Framework :: Plone :: 4.3
Classifier: Intended Audience :: System Administrators
Classifier: License :: OSI Approved :: GNU General Public License v2 (GPLv2)
Classifier: Operating System :: OS Independent
Classifier: Programming Language :: Python
Classifier: Programming Language :: Python :: 2.6
Classifier: Programming Language :: Python :: 2.7
Classifier: Topic :: Software Development :: Libraries :: Python Modules
